exports/__init__.py
exports/api_handler.py
exports/async_handler.py
exports/cache_handler.py
exports/client.py
exports/context.py
exports/django.py
exports/error.py
exports/fastapi.py
exports/flask.py
exports/json_formatter.py
exports/network.py
exports/performance.py
loggier/__init__.py
loggier/client.py
loggier/formatters/__init__.py
loggier/formatters/json_formatter.py
loggier/handlers/__init__.py
loggier/handlers/api_handler.py
loggier/handlers/async_handler.py
loggier/handlers/cache_handler.py
loggier/integrations/__init__.py
loggier/integrations/django.py
loggier/integrations/fastapi.py
loggier/integrations/flask.py
loggier/monitoring/__init__.py
loggier/monitoring/performance.py
loggier/utils/__init__.py
loggier/utils/context.py
loggier/utils/error.py
loggier/utils/network.py
loggier-0.1.9.dist-info/licenses/LICENSE
loggier-0.1.9.dist-info/METADATA
loggier-0.1.9.dist-info/WHEEL
loggier-0.1.9.dist-info/top_level.txt
loggier-0.1.9.dist-info/RECORD
