Metadata-Version: 2.4
Name: loggier
Version: 0.1.9
Summary: Log management and error tracking library for modern Python applications.
Home-page: https://github.com/yigitaltintas/loggier
Author: Yigit ALTINTAS
Author-email: Loggier Team <info@loggier.app>
License: MIT
Project-URL: Homepage, https://loggier.app
Project-URL: Documentation, https://docs.loggier.app
Project-URL: Repository, https://github.com/loggier/loggier
Project-URL: Issues, https://github.com/loggier/loggier/issues
Keywords: logging,error-tracking,monitoring,apm,performance
Classifier: Development Status :: 4 - Beta
Classifier: Intended Audience :: Developers
Classifier: License :: OSI Approved :: MIT License
Classifier: Programming Language :: Python :: 3
Classifier: Programming Language :: Python :: 3.8
Classifier: Programming Language :: Python :: 3.9
Classifier: Programming Language :: Python :: 3.10
Classifier: Programming Language :: Python :: 3.11
Classifier: Topic :: Software Development :: Libraries :: Python Modules
Classifier: Topic :: System :: Logging
Classifier: Topic :: System :: Monitoring
Requires-Python: >=3.6
License-File: LICENSE
Requires-Dist: requests>=2.25.0
Requires-Dist: urllib3>=1.26.0
Provides-Extra: test
Requires-Dist: pytest>=7.0.0; extra == "test"
Requires-Dist: pytest-cov>=3.0.0; extra == "test"
Requires-Dist: requests-mock>=1.9.0; extra == "test"
Provides-Extra: django
Requires-Dist: django>=3.2.0; extra == "django"
Provides-Extra: flask
Requires-Dist: flask>=2.0.0; extra == "flask"
Provides-Extra: fastapi
Requires-Dist: fastapi>=0.70.0; extra == "fastapi"
Requires-Dist: starlette>=0.16.0; extra == "fastapi"
Dynamic: author
Dynamic: home-page
Dynamic: license-file
Dynamic: requires-python
